pennylane_lightning/core/CMakeLists.txt
pennylane_lightning/core/__init__.py
pennylane_lightning/core/_version.py
pennylane_lightning/core/algorithms/AdjointJacobianBase.hpp
pennylane_lightning/core/algorithms/CMakeLists.txt
pennylane_lightning/core/algorithms/JacobianData.hpp
pennylane_lightning/core/algorithms/tests/CMakeLists.txt
pennylane_lightning/core/algorithms/tests/Test_AdjointJacobian.cpp
pennylane_lightning/core/algorithms/tests/runner_algorithms.cpp
pennylane_lightning/core/algorithms/tests/mpi/Test_AdjointJacobianMPI.cpp
pennylane_lightning/core/algorithms/tests/mpi/runner_algorithms_mpi.cpp
pennylane_lightning/core/bindings/Bindings.cpp
pennylane_lightning/core/bindings/Bindings.hpp
pennylane_lightning/core/bindings/BindingsCudaUtils.hpp
pennylane_lightning/core/bindings/BindingsMPI.hpp
pennylane_lightning/core/bindings/BindingsUtils.hpp
pennylane_lightning/core/bindings/CMakeLists.txt
pennylane_lightning/core/catalyst/CMakeLists.txt
pennylane_lightning/core/catalyst/LightningQubitManager.hpp
pennylane_lightning/core/catalyst/tests/CMakeLists.txt
pennylane_lightning/core/catalyst/tests/Test_LightningDriver.cpp
pennylane_lightning/core/catalyst/tests/Test_LightningQubitManager.cpp
pennylane_lightning/core/catalyst/tests/runner_catalyst.cpp
pennylane_lightning/core/gates/CMakeLists.txt
pennylane_lightning/core/gates/Constant.hpp
pennylane_lightning/core/gates/GateOperation.hpp
pennylane_lightning/core/gates/Gates.hpp
pennylane_lightning/core/measurements/.clang-tidy
pennylane_lightning/core/measurements/CMakeLists.txt
pennylane_lightning/core/measurements/MeasurementsBase.hpp
pennylane_lightning/core/measurements/tests/CMakeLists.txt
pennylane_lightning/core/measurements/tests/Test_MeasurementsBase.cpp
pennylane_lightning/core/measurements/tests/runner_measurements.cpp
pennylane_lightning/core/measurements/tests/mpi/Test_MeasurementsBaseMPI.cpp
pennylane_lightning/core/measurements/tests/mpi/runner_measurements_mpi.cpp
pennylane_lightning-0.43.0.dist-info/licenses/LICENSE
pennylane_lightning-0.43.0.dist-info/METADATA
pennylane_lightning-0.43.0.dist-info/WHEEL
pennylane_lightning-0.43.0.dist-info/entry_points.txt
pennylane_lightning-0.43.0.dist-info/top_level.txt
pennylane_lightning-0.43.0.dist-info/RECORD
